doorda_sdk/__init__.py
doorda_sdk/host/__init__.py
doorda_sdk/host/client.py
doorda_sdk/util/__init__.py
doorda_sdk/util/common.py
doorda_sdk/util/decorators.py
doorda_sdk/util/exc.py
doorda_sdk/util/permissions_tree.py
doorda_sdk-2.0.1.dist-info/LICENSE
doorda_sdk-2.0.1.dist-info/METADATA
doorda_sdk-2.0.1.dist-info/WHEEL
doorda_sdk-2.0.1.dist-info/top_level.txt
doorda_sdk-2.0.1.dist-info/RECORD
