Metadata-Version: 2.1
Name: doorda-sdk
Version: 2.0.1
Summary: Doorda SDK for access to Hosted Platform
Home-page: https://github.com/doorda/doorda-python-sdk
Download-URL: https://github.com/Doorda/doorda-python-sdk/releases/latest
Author: Samuel Tan
Author-email: samuel@doorda.com
License: Apache License 2.0
Classifier: Programming Language :: Python :: 3
Classifier: Programming Language :: Python :: 3.6
Classifier: Programming Language :: Python :: 3.7
Classifier: Programming Language :: Python :: 3.8
Classifier: License :: OSI Approved :: Apache Software License
Classifier: Operating System :: OS Independent
Classifier: Intended Audience :: Developers
License-File: LICENSE
Requires-Dist: future (>=0.16.0)
Requires-Dist: requests (>=2.21.0)
